sqlalchemy_guid/__init__.py
sqlalchemy_guid/guid.py
sqlalchemy_guid-1.0.2.dist-info/LICENSE
sqlalchemy_guid-1.0.2.dist-info/METADATA
sqlalchemy_guid-1.0.2.dist-info/WHEEL
sqlalchemy_guid-1.0.2.dist-info/RECORD
