Metadata-Version: 2.1
Name: sqlalchemy-guid
Version: 1.0.2
Summary: 
License: MIT
Author: Alexander Karateev
Author-email: administrator@gintr1k.space
Requires-Python: >=3.7,<4.0
Classifier: License :: OSI Approved :: MIT License
Classifier: Programming Language :: Python :: 3
Classifier: Programming Language :: Python :: 3.7
Classifier: Programming Language :: Python :: 3.8
Classifier: Programming Language :: Python :: 3.9
Classifier: Programming Language :: Python :: 3.10
Classifier: Programming Language :: Python :: 3.11
Requires-Dist: sqlalchemy (>1.0,<3.0)
Project-URL: Source, https://github.com/gintr1k/sqlalchemy-guid
